irdatacleaning/__init__.py
irdatacleaning/datacorrelation.py
irdatacleaning/datadiscovery.py
irdatacleaning/encoder2.py
irdatacleaning/featur_scaling.py
irdatacleaning/imagevis.py
irdatacleaning/inconsistent_data.py
irdatacleaning/missingvalues.py
irdatacleaning/resource.py
irdatacleaning/stringtodatetime.py
irdatacleaning-2022.1.19.dist-info/LICENSE
irdatacleaning-2022.1.19.dist-info/METADATA
irdatacleaning-2022.1.19.dist-info/WHEEL
irdatacleaning-2022.1.19.dist-info/top_level.txt
irdatacleaning-2022.1.19.dist-info/RECORD
