Metadata-Version: 2.1
Name: irdatacleaning
Version: 2022.1.19
Summary: module designed to make your data preprocessing experience easier
Home-page: UNKNOWN
Author: Islander Intelligence (William McKeon)
Author-email: <IslanderRobotics@gmail.com>
License: UNKNOWN
Keywords: python,Machine Learning,Artificial Intelligence,Data Science,Data Cleaning
Platform: UNKNOWN
License-File: LICENSE
Requires-Dist: pandas
Requires-Dist: matplotlib
Requires-Dist: scikit-learn
Requires-Dist: IslanderDataPreprocessing
Requires-Dist: numpy
Requires-Dist: opencv-python
